{
	"datas": {
		"T_JZG_GZJL_QUERY": {
			"totalSize": 1,
			"pageSize": 1000,
			"rows": [{
				"WID": "pbn9uzv4-qj01-vk8d-cgko-qdp7n7rhwfk0",
				"JZGBH": "2008068",
				"QSRQ": "2016-03",
				"JZRQ": "2016-05",
				"GJDQDM": "156",
				"SZDWMC": "金智教育",
				"CSGZNR": "软件开发",
				"CRDZZW": "无",
				"CRZYJSZWDM": "030",
				"ZMR": "张三",
				"BZ": "备注内容",
				"TBRQ": null,
				"TBLX": null,
				"CZRQ": null,
				"CZZ": null,
				"CZZXM": "汪维亮",
				"GJDQDM_DISPLAY": "中华人民共和国",
				"CRZYJSZWDM_DISPLAY": "技工学校教师"
			}]
		}
	},
	"code": "0"
}